{"content_hash": "4786b09136d5b0cd799047814e8324f4", "document_id": 28, "term_frequency_dict": {"enough": 1, "campu": 1, "coach": 2, "commut": 1, "basketbal": 3, "sport": 1, "fire": 3, "titl": 1, "empti": 1, "media": 1, "tourney": 1, "arena": 1, "ark": 1, "men": 1, "sit": 1, "make": 1, "heartfelt": 1, "particular": 1, "show": 1, "belt": 2, "indiana": 1, "mostli": 1, "past": 1, "uta": 4, "gener": 1, "kind": 1, "pro": 1, "staff": 1, "sellout": 1, "want": 1, "colleg": 1, "monday": 1, "n't": 1, "coven": 1, "need": 1, "larg": 1, "anywher": 1, "region": 1, "interest": 1, "lot": 1, "without": 1, "assist": 1, "receiv": 1, "good": 1, "win": 2, "issu": 1, "ncaa": 2, "statement": 1, "at-larg": 1, "sun": 2, "big": 1, "game": 2, "routin": 1, "social": 1, "peopl": 1, "center": 1, "top": 1, "home": 1, "man": 1, "scott": 1, "sweep": 1, "prefer": 1, "never": 1, "three": 1, "park": 1, "must": 1, "maverick": 1, "chang": 1, "shortli": 1, "jone": 1, "footbal": 2, "look": 1, "schollmaier": 1, "metropolitan": 1, "confer": 1, "team": 2, "season": 2, "tcu": 1, "bid": 1, "cross": 2, "tournament": 2}}