{"0": "abil", "1": "accept", "2": "accord", "3": "accus", "4": "accusers\u2014mayella", "5": "ace", "6": "acknowledg", "7": "act", "8": "action", "9": "activ", "10": "actual", "11": "addit", "12": "address", "13": "administr", "14": "adult", "15": "advanc", "16": "advertis", "17": "affect", "18": "afternoon", "19": "age", "20": "agent", "21": "agre", "22": "ahead", "23": "alabama", "24": "alejandroproctor", "25": "alexandra", "26": "algorithm", "27": "all-tim", "28": "allow", "29": "almost", "30": "alon", "31": "along", "32": "also", "33": "although", "34": "altuv", "35": "alway", "36": "amaz", "37": "amend", "38": "america", "39": "american", "40": "amid", "41": "analysi", "42": "ancestor", "43": "angel", "44": "ankl", "45": "announc", "46": "anoth", "47": "anywher", "48": "appear", "49": "appoint", "50": "approxim", "51": "apr", "52": "arena", "53": "argu", "54": "ark", "55": "arlington", "56": "arm", "57": "armi", "58": "around", "59": "array", "60": "arriv", "61": "arthur", "62": "articl", "63": "ask", "64": "assess", "65": "assign", "66": "assist", "67": "associ", "68": "astro", "69": "at-larg", "70": "atlanta", "71": "attack", "72": "atticu", "73": "auburn", "74": "aunt", "75": "avail", "76": "averag", "77": "avert", "78": "away", "79": "back", "80": "backboard", "81": "background", "82": "bad", "83": "badli", "84": "balconi", "85": "ball", "86": "ballpark", "87": "barrag", "88": "basebal", "89": "baselin", "90": "basket", "91": "basketbal", "92": "batter", "93": "bay", "94": "beat", "95": "beauti", "96": "becom", "97": "befriend", "98": "beg", "99": "begin", "100": "behind", "101": "beig", "102": "believ", "103": "belt", "104": "best", "105": "betdsi", "106": "betsdi", "107": "better", "108": "bid", "109": "big", "110": "bigram", "111": "bird", "112": "birdi", "113": "black", "114": "blackboard", "115": "bleacher", "116": "bleep", "117": "block", "118": "bob", "119": "bodi", "120": "bogey", "121": "boo", "122": "boolean", "123": "boom", "124": "bounc", "125": "boy", "126": "braveri", "127": "break", "128": "breezi", "129": "brief", "130": "broken", "131": "brother", "132": "brown", "133": "brush", "134": "bryant", "135": "bryson", "136": "buildingon", "137": "buildingthre", "138": "buildingtwo", "139": "busi", "140": "calcul", "141": "calendar", "142": "call", "143": "calpurnia", "144": "came", "145": "campu", "146": "canva", "147": "captain", "148": "caption", "149": "care", "150": "career", "151": "carri", "152": "carrot2", "153": "caruth", "154": "cash", "155": "cast", "156": "cat", "157": "catch", "158": "caught", "159": "cb", "160": "celebr", "161": "center", "162": "certain", "163": "champagn", "164": "champion", "165": "championship", "166": "chanc", "167": "chang", "168": "charact", "169": "charg", "170": "chaser", "171": "cheer", "172": "children", "173": "choo", "174": "chpt", "175": "chrisproctor", "176": "circumst", "177": "citizen", "178": "claim", "179": "class", "180": "classic", "181": "classif", "182": "clear", "183": "clearli", "184": "close", "185": "close-knit", "186": "club", "187": "cluster", "188": "coach", "189": "cole", "190": "colleg", "191": "color", "192": "come", "193": "comment", "194": "common", "195": "commut", "196": "compani", "197": "competit", "198": "complet", "199": "complex", "200": "compress", "201": "condit", "202": "confer", "203": "confus", "204": "constant", "205": "contact", "206": "contend", "207": "content", "208": "continu", "209": "contribut", "210": "convict", "211": "cost", "212": "could", "213": "counti", "214": "courag", "215": "cours", "216": "court", "217": "coven", "218": "cover", "219": "cow", "220": "cowboy", "221": "crane", "222": "crawl", "223": "creat", "224": "credibl", "225": "credit", "226": "critic", "227": "cross", "228": "cse", "229": "cut", "230": "dalla", "231": "danger", "232": "dark", "233": "databas", "234": "date", "235": "day", "236": "dechambeau", "237": "decis", "238": "defend", "239": "defens", "240": "defenseless", "241": "definit", "242": "demand", "243": "demo", "244": "departur", "245": "depend", "246": "depress", "247": "deserv", "248": "despit", "249": "destroy", "250": "devast", "251": "develop", "252": "dez", "253": "di", "254": "diamet", "255": "die", "256": "differ", "257": "difficult", "258": "dill", "259": "dip", "260": "dirk", "261": "disabl", "262": "disappear", "263": "disappoint", "264": "disapprov", "265": "discov", "266": "dispers", "267": "display", "268": "distanc", "269": "diyanginclass3/8/2018", "270": "do_calc", "271": "document", "272": "document.createel", "273": "document.getelementbyid", "274": "document.getelementsbytagnam", "275": "document.location.protocol", "276": "dog", "277": "domin", "278": "done", "279": "donni", "280": "door", "281": "doubl", "282": "doubt", "283": "draft", "284": "draw", "285": "drew", "286": "dribbl", "287": "driveway", "288": "drop", "289": "drunk\u2014ar", "290": "dubos", "291": "due", "292": "dump", "293": "dustin", "294": "eagl", "295": "echo", "296": "educ", "297": "efe", "298": "els", "299": "elud", "300": "email", "301": "empti", "302": "end", "303": "enjoy", "304": "enough", "305": "equal", "306": "eras", "307": "error", "308": "escap", "309": "establish", "310": "ethic", "311": "evalu", "312": "even", "313": "event", "314": "eventu", "315": "ever", "316": "everi", "317": "everyon", "318": "evid", "319": "ewel", "320": "exam", "321": "exam1", "322": "exampl", "323": "example2", "324": "exhibit", "325": "expans", "326": "expect", "327": "explain", "328": "extend", "329": "extraordinari", "330": "eyebal", "331": "face", "332": "factor", "333": "fairli", "334": "faith", "335": "fall", "336": "fame", "337": "famili", "338": "fan", "339": "fantas", "340": "fascin", "341": "fast", "342": "father", "343": "fathom", "344": "favorit", "345": "fear", "346": "feb", "347": "fed", "348": "feed", "349": "feedback", "350": "feet", "351": "fell", "352": "fellow", "353": "feminin", "354": "fever", "355": "fiction", "356": "fictiti", "357": "field", "358": "fight", "359": "figur", "360": "file", "361": "final", "362": "finch", "363": "find", "364": "finish", "365": "fire", "366": "first", "367": "fist", "368": "five", "369": "flight", "370": "floor", "371": "fmoor", "372": "focus", "373": "font-famili", "374": "font-size:1.5em", "375": "font-styl", "376": "footbal", "377": "footer", "378": "forc", "379": "forese", "380": "former", "381": "forward", "382": "foul", "383": "found", "384": "four-gam", "385": "franchis", "386": "free", "387": "freeman", "388": "frequenc", "389": "friday", "390": "friendless", "391": "friendli", "392": "friendship", "393": "front", "394": "full", "395": "fun", "396": "function", "397": "futur", "398": "ga.async", "399": "ga.src", "400": "ga.typ", "401": "gain", "402": "game", "403": "garrett", "404": "gener", "405": "genuinel", "406": "gestur", "407": "get", "408": "gift", "409": "girl", "410": "given", "411": "gloriou", "412": "go", "413": "goal", "414": "god", "415": "godo", "416": "goe", "417": "gold", "418": "golden", "419": "golf", "420": "golfer", "421": "good", "422": "goodby", "423": "googl", "424": "got", "425": "great", "426": "green", "427": "group", "428": "grow", "429": "guidepost", "430": "guis", "431": "guy", "432": "haa", "433": "hadn't", "434": "half", "435": "hall", "436": "halloween", "437": "hamel", "438": "hapless", "439": "happen", "440": "happi", "441": "harbour", "442": "hate", "443": "hawk", "444": "head", "445": "hear", "446": "hearitag", "447": "heartfelt", "448": "height:300px", "449": "help", "450": "heproctor", "451": "hero", "452": "hesit", "453": "hidden", "454": "hierarch", "455": "high", "456": "highlight", "457": "histori", "458": "hit", "459": "hmwk", "460": "hmwk4", "461": "holder", "462": "hole", "463": "home", "464": "honor", "465": "hoop", "466": "hope", "467": "horrend", "468": "hous", "469": "housekeep", "470": "houston", "471": "http", "472": "humili", "473": "i-1", "474": "ill", "475": "imagin", "476": "impact", "477": "implement", "478": "incent", "479": "inch", "480": "inclass", "481": "includ", "482": "index", "483": "indiana", "484": "infield", "485": "influenc", "486": "inform", "487": "injuri", "488": "inline-block", "489": "inning", "490": "innoc", "491": "instead", "492": "instinct", "493": "insult", "494": "intent", "495": "interest", "496": "internet", "497": "introduct", "498": "invent", "499": "invers", "500": "invit", "501": "iowa", "502": "issu", "503": "j-1", "504": "jack", "505": "jame", "506": "jan", "507": "japanes", "508": "jason", "509": "javal", "510": "javascript", "511": "jay", "512": "jean", "513": "jem", "514": "jim", "515": "join", "516": "jone", "517": "jose", "518": "judg", "519": "jumpstart", "520": "junctur", "521": "juri", "522": "justic", "523": "justifi", "524": "justin", "525": "k-mean", "526": "keep", "527": "kelli", "528": "kick", "529": "kill", "530": "kind", "531": "kindli", "532": "knife", "533": "know", "534": "kraft", "535": "kriv", "536": "lack", "537": "ladi", "538": "lamb", "539": "lane", "540": "larg", "541": "last", "542": "late", "543": "later", "544": "latest", "545": "lawyer", "546": "lead", "547": "leader", "548": "leagu", "549": "learn", "550": "leav", "551": "left", "552": "legion", "553": "len_", "554": "len_s+1", "555": "len_s1", "556": "len_s2", "557": "len_t", "558": "len_t+1", "559": "lesson", "560": "let", "561": "letter", "562": "level", "563": "levelhead", "564": "levenshtein", "565": "levenshteindist", "566": "liangproctor", "567": "lie", "568": "life", "569": "lifelong", "570": "like", "571": "limited-contact", "572": "line", "573": "link", "574": "list", "575": "littl", "576": "live", "577": "lo", "578": "locat", "579": "long", "580": "look", "581": "lopez", "582": "lose", "583": "losest", "584": "loss", "585": "lot", "586": "louis", "587": "love", "588": "lower", "589": "lucen", "590": "lure", "591": "lyle.smu.edu", "592": "lynch", "593": "m/w", "594": "machin", "595": "made", "596": "made-mad", "597": "magic", "598": "main", "599": "maintain", "600": "major", "601": "make", "602": "man", "603": "mandat", "604": "mani", "605": "mann", "606": "mar", "607": "margin-top:15px", "608": "margin:0", "609": "mari", "610": "mark", "611": "mary1234", "612": "master", "613": "match", "614": "math.min", "615": "mav", "616": "maverick", "617": "may", "618": "maycomb", "619": "mayella", "620": "mcgee", "621": "meaning", "622": "media", "623": "mediocr", "624": "memori", "625": "men", "626": "menac", "627": "mengliproctor", "628": "mercat", "629": "met", "630": "methodist", "631": "metropolitan", "632": "mickelson", "633": "middle-ag", "634": "midway", "635": "million", "636": "mind", "637": "minut", "638": "miss", "639": "misubishi", "640": "mix", "641": "mlb", "642": "mob", "643": "mockingbird", "644": "model", "645": "monday", "646": "money", "647": "monospac", "648": "month", "649": "moor", "650": "mostli", "651": "mount", "652": "move", "653": "much", "654": "multipl", "655": "must", "656": "mvp", "657": "myform.distance.valu", "658": "myform.string1.valu", "659": "myform.string2.valu", "660": "mysteri", "661": "n't", "662": "naismith", "663": "naiv", "664": "name", "665": "nba", "666": "ncaa", "667": "nearer", "668": "nearest", "669": "nearli", "670": "necessarili", "671": "need", "672": "neighbor", "673": "neighborhood", "674": "nelson", "675": "nephew", "676": "never", "677": "new", "678": "news", "679": "next", "680": "nice", "681": "nicknam", "682": "nigger-lov", "683": "night", "684": "non-word", "685": "normal", "686": "noth", "687": "novel", "688": "nowitzki", "689": "number", "690": "numberpersonlocationrequest", "691": "object", "692": "obsess", "693": "octob", "694": "oddsmak", "695": "off-season", "696": "offens", "697": "offici", "698": "often", "699": "ohtani", "700": "old", "701": "older", "702": "one", "703": "one-on-on", "704": "onestrok", "705": "onlin", "706": "open", "707": "opinion", "708": "opposit", "709": "optimist", "710": "option", "711": "oracl", "712": "organ", "713": "oscar", "714": "output", "715": "outsid", "716": "overflow-i", "717": "overhaul", "718": "overlap", "719": "overlap.join", "720": "overlap.push", "721": "overlay", "722": "overtim", "723": "overview", "724": "owner", "725": "padding:5px", "726": "page", "727": "pageant", "728": "pagerank", "729": "par", "730": "parent", "731": "park", "732": "part", "733": "particular", "734": "pass", "735": "passion", "736": "past", "737": "pay", "738": "peac", "739": "penalti", "740": "peopl", "741": "per", "742": "perfect", "743": "perform", "744": "peril", "745": "permuterm", "746": "person", "747": "perspect", "748": "pga", "749": "phd", "750": "phil", "751": "physic", "752": "pick", "753": "pitch", "754": "place", "755": "plan", "756": "plant", "757": "play", "758": "player", "759": "playoff", "760": "plenti", "761": "poem", "762": "point", "763": "polici", "764": "pop", "765": "porch", "766": "porter", "767": "posit", "768": "post", "769": "poulter", "770": "power", "771": "prefer", "772": "preliminari", "773": "present", "774": "presid", "775": "previou", "776": "primarili", "777": "principl", "778": "prison", "779": "pro", "780": "problem", "781": "proctor", "782": "profession", "783": "project", "784": "promis", "785": "proud", "786": "prove", "787": "provid", "788": "prudenc", "789": "publicli", "790": "purchas", "791": "put", "792": "putrid", "793": "puzzl", "794": "qizhiproctor", "795": "queri", "796": "quest", "797": "quick", "798": "quit", "799": "racial", "800": "radley", "801": "rais", "802": "ranger", "803": "rank", "804": "rape", "805": "ray", "806": "rbc", "807": "read", "808": "realiz", "809": "realli", "810": "reason", "811": "rebound", "812": "rebuilt", "813": "receiv", "814": "recept", "815": "reclus", "816": "record", "817": "rectangular", "818": "refer", "819": "reflect", "820": "regard", "821": "region", "822": "regist", "823": "regret", "824": "regul", "825": "regular", "826": "reign", "827": "relat", "828": "relationship", "829": "releas", "830": "relev", "831": "reloc", "832": "remain", "833": "remind", "834": "repaid", "835": "repeatedli", "836": "report", "837": "repres", "838": "requir", "839": "rescu", "840": "reserv", "841": "respect", "842": "respond", "843": "respons", "844": "rest", "845": "restrain", "846": "resurg", "847": "rete", "848": "retriev", "849": "return", "850": "rev", "851": "reveng", "852": "review", "853": "richard", "854": "right", "855": "rise", "856": "roadmap", "857": "robinson", "858": "role", "859": "roll", "860": "rori", "861": "rotat", "862": "rough", "863": "round", "864": "routin", "865": "rule", "866": "rumor", "867": "run", "868": "s.charat", "869": "s.parentnode.insertbefor", "870": "s1.length", "871": "s2.length", "872": "said", "873": "sale", "874": "sat", "875": "saturday", "876": "save", "877": "say", "878": "schedul", "879": "schollmaier", "880": "school", "881": "score", "882": "scott", "883": "scout", "884": "scroll", "885": "scum", "886": "seahawk", "887": "seamless", "888": "search", "889": "season", "890": "seat", "891": "second", "892": "secondari", "893": "see", "894": "seen", "895": "sellout", "896": "send", "897": "sens", "898": "sentenc", "899": "seri", "900": "sever", "901": "sexual", "902": "shaken", "903": "shame", "904": "shelv", "905": "sheriff", "906": "shin", "907": "shirtsleev", "908": "shohei", "909": "shoot", "910": "shortli", "911": "shot", "912": "show", "913": "shred", "914": "shrug", "915": "side", "916": "signific", "917": "similar", "918": "simpli", "919": "simplli", "920": "sinc", "921": "sit", "922": "site", "923": "situat", "924": "six-year-old", "925": "slur", "926": "smack", "927": "small", "928": "smu", "929": "smu.edu", "930": "social", "931": "softwar", "932": "sole", "933": "solv", "934": "someon", "935": "someth", "936": "sometim", "937": "somewher", "938": "soo", "939": "sore", "940": "soundex", "941": "sourc", "942": "southern", "943": "space", "944": "span", "945": "spell", "946": "spend", "947": "spit", "948": "split", "949": "spoke", "950": "sport", "951": "sportsbook", "952": "spring", "953": "staff", "954": "stand", "955": "star", "956": "start", "957": "state", "958": "statement", "959": "station", "960": "statu", "961": "stay", "962": "steamrol", "963": "stem", "964": "stemmed.join", "965": "stemmed.push", "966": "stemmer", "967": "stephen", "968": "still", "969": "stop", "970": "stori", "971": "street", "972": "strength", "973": "stress", "974": "stretch", "975": "strike", "976": "string", "977": "stroke", "978": "stroll", "979": "struggl", "980": "student", "981": "suddenli", "982": "sugarloaf", "983": "summer", "984": "sun", "985": "sunday", "986": "sure", "987": "surgeri", "988": "suspect", "989": "swarm", "990": "sweep", "991": "switch", "992": "syke", "993": "syllabu", "994": "system", "995": "t.charat", "996": "t/th", "997": "take", "998": "talk", "999": "tan", "1000": "tate", "1001": "taught", "1002": "taunt", "1003": "taylor", "1004": "tcu", "1005": "team", "1006": "teammat", "1007": "tee", "1008": "tell", "1009": "temper", "1010": "tempt", "1011": "temptat", "1012": "tendenc", "1013": "tent", "1014": "terenc", "1015": "term", "1016": "terribl", "1017": "terrifi", "1018": "test", "1019": "test.replac", "1020": "test.split", "1021": "texa", "1022": "text", "1023": "text-align", "1024": "textarea", "1025": "textfil", "1026": "theme", "1027": "thick", "1028": "thing", "1029": "think", "1030": "thompson", "1031": "though", "1032": "three", "1033": "three-on-thre", "1034": "three-point", "1035": "threesom", "1036": "throw", "1037": "thursday", "1038": "tianqiinclass3/5/2018", "1039": "ticket", "1040": "tie", "1041": "tiger", "1042": "time", "1043": "tire", "1044": "titl", "1045": "told", "1046": "toler", "1047": "tom", "1048": "tomboy", "1049": "took", "1050": "top", "1051": "topic", "1052": "total", "1053": "touch", "1054": "touchdown", "1055": "tought", "1056": "tour", "1057": "tournament", "1058": "tourney", "1059": "toward", "1060": "town", "1061": "tpc", "1062": "train", "1063": "transit", "1064": "tree", "1065": "tri", "1066": "trial", "1067": "trip", "1068": "trophi", "1069": "troubl", "1070": "trout", "1071": "true", "1072": "truli", "1073": "tuesday", "1074": "tuesday/thursday", "1075": "turn", "1076": "two", "1077": "two-on-two", "1078": "type", "1079": "ultim", "1080": "uncl", "1081": "undeer", "1082": "undergo", "1083": "understand", "1084": "unit", "1085": "univers", "1086": "unquest", "1087": "use", "1088": "user", "1089": "uta", "1090": "valuabl", "1091": "var", "1092": "vector", "1093": "verbal", "1094": "version", "1095": "via", "1096": "vice", "1097": "victori", "1098": "view", "1099": "visit", "1100": "vote", "1101": "vow", "1102": "walk", "1103": "want", "1104": "warrior", "1105": "watch", "1106": "water", "1107": "way", "1108": "weak", "1109": "weater", "1110": "web", "1111": "wednesday", "1112": "week", "1113": "weekend", "1114": "went", "1115": "west", "1116": "whatev", "1117": "white", "1118": "white-spac", "1119": "whole", "1120": "wide", "1121": "widow", "1122": "width:600px", "1123": "wild", "1124": "wildcard", "1125": "win", "1126": "wish", "1127": "without", "1128": "woman", "1129": "wonder", "1130": "wood", "1131": "word", "1132": "wordlist", "1133": "world", "1134": "worth", "1135": "would", "1136": "wring", "1137": "writer", "1138": "year", "1139": "yield", "1140": "young"}